[
  {
    "brand": "Molinard",
    "name": "Crème 24",
    "release_year": null,
    "concentration": "edp",
    "fragrance_family": null,
    "gender": "unisex",
    "top_notes": [],
    "heart_notes": [],
    "base_notes": [],
    "top_accords": [],
    "accord_intensity": {},
    "community_longevity": null,
    "community_sillage": null,
    "community_projection": null,
    "compliment_score": null,
    "versatility_score": null,
    "office_safe_score": null,
    "price_tier": null,
    "retail_msrp_usd_cents": 1408,
    "prices": [
      {
        "retailer": "molinard-direct",
        "size_ml": 60,
        "price_usd_cents": 1408,
        "is_decant": false,
        "url": "https://www.molinard.com/products/creme-24"
      },
      {
        "retailer": "molinard-direct",
        "size_ml": 60,
        "price_usd_cents": 3917,
        "is_decant": false,
        "url": "https://www.molinard.com/products/creme-24"
      },
      {
        "retailer": "molinard-direct",
        "size_ml": 60,
        "price_usd_cents": 7417,
        "is_decant": false,
        "url": "https://www.molinard.com/products/creme-24"
      },
      {
        "retailer": "molinard-direct",
        "size_ml": 60,
        "price_usd_cents": 13500,
        "is_decant": false,
        "url": "https://www.molinard.com/products/creme-24"
      }
    ],
    "image_url": "https://cdn.shopify.com/s/files/1/0722/1421/7014/files/8197442830646-7618653bf1f121908e1ecf12a81879712da2385a.jpg?v=1768220441",
    "source": "molinard",
    "source_url": "https://www.molinard.com/products/creme-24",
    "sources": [
      "molinard"
    ]
  },
  {
    "brand": "Molinard",
    "name": "Crème à Raser Rasoline",
    "release_year": null,
    "concentration": "edp",
    "fragrance_family": null,
    "gender": "unisex",
    "top_notes": [],
    "heart_notes": [],
    "base_notes": [],
    "top_accords": [],
    "accord_intensity": {},
    "community_longevity": null,
    "community_sillage": null,
    "community_projection": null,
    "compliment_score": null,
    "versatility_score": null,
    "office_safe_score": null,
    "price_tier": null,
    "retail_msrp_usd_cents": 1325,
    "prices": [
      {
        "retailer": "molinard-direct",
        "size_ml": 100,
        "price_usd_cents": 1325,
        "is_decant": false,
        "url": "https://www.molinard.com/products/creme-a-raser-rasoline"
      },
      {
        "retailer": "molinard-direct",
        "size_ml": 100,
        "price_usd_cents": 3667,
        "is_decant": false,
        "url": "https://www.molinard.com/products/creme-a-raser-rasoline"
      },
      {
        "retailer": "molinard-direct",
        "size_ml": 100,
        "price_usd_cents": 7000,
        "is_decant": false,
        "url": "https://www.molinard.com/products/creme-a-raser-rasoline"
      },
      {
        "retailer": "molinard-direct",
        "size_ml": 100,
        "price_usd_cents": 12667,
        "is_decant": false,
        "url": "https://www.molinard.com/products/creme-a-raser-rasoline"
      }
    ],
    "image_url": "https://cdn.shopify.com/s/files/1/0722/1421/7014/files/9457942233423-43bc6b68b695613c08dbcc901a1f2fc828e0c42b_e0da2db8-fb18-48da-bda1-0b13a3c8d4be.jpg?v=1768220459",
    "source": "molinard",
    "source_url": "https://www.molinard.com/products/creme-a-raser-rasoline",
    "sources": [
      "molinard"
    ]
  },
  {
    "brand": "Molinard",
    "name": "Eau de Cologne France",
    "release_year": null,
    "concentration": "cologne",
    "fragrance_family": null,
    "gender": "unisex",
    "top_notes": [],
    "heart_notes": [],
    "base_notes": [],
    "top_accords": [],
    "accord_intensity": {},
    "community_longevity": null,
    "community_sillage": null,
    "community_projection": null,
    "compliment_score": null,
    "versatility_score": null,
    "office_safe_score": null,
    "price_tier": null,
    "retail_msrp_usd_cents": null,
    "prices": [],
    "image_url": "https://cdn.shopify.com/s/files/1/0722/1421/7014/files/8745297674575-f622d1f8cf4febf0bc90cf61a6595f9fa25d7ab4_aa70b8f8-b887-4732-84e0-23f253c68bf6.jpg?v=1768221094",
    "source": "molinard",
    "source_url": "https://www.molinard.com/products/cologne-france",
    "sources": [
      "molinard"
    ]
  },
  {
    "brand": "Molinard",
    "name": "Eau de Parfum À Corps Cuivré",
    "release_year": null,
    "concentration": "edp",
    "fragrance_family": null,
    "gender": "unisex",
    "top_notes": [],
    "heart_notes": [],
    "base_notes": [],
    "top_accords": [],
    "accord_intensity": {},
    "community_longevity": null,
    "community_sillage": null,
    "community_projection": null,
    "compliment_score": null,
    "versatility_score": null,
    "office_safe_score": null,
    "price_tier": null,
    "retail_msrp_usd_cents": null,
    "prices": [],
    "image_url": "https://cdn.shopify.com/s/files/1/0722/1421/7014/files/8540446359887-4ed1a60a645c504c053fdae08169355ea3359d15.jpg?v=1768397654",
    "source": "molinard",
    "source_url": "https://www.molinard.com/products/eau-de-parfum-a-corps-cuivre",
    "sources": [
      "molinard"
    ]
  },
  {
    "brand": "Molinard",
    "name": "Eau de Parfum Acqua Lotus",
    "release_year": null,
    "concentration": "edp",
    "fragrance_family": null,
    "gender": "unisex",
    "top_notes": [],
    "heart_notes": [],
    "base_notes": [],
    "top_accords": [],
    "accord_intensity": {},
    "community_longevity": null,
    "community_sillage": null,
    "community_projection": null,
    "compliment_score": null,
    "versatility_score": null,
    "office_safe_score": null,
    "price_tier": null,
    "retail_msrp_usd_cents": null,
    "prices": [],
    "image_url": "https://cdn.shopify.com/s/files/1/0722/1421/7014/files/8658820759887-19a649ab043b4c8a01a01a0205927c52ac2240bd.jpg?v=1768397613",
    "source": "molinard",
    "source_url": "https://www.molinard.com/products/eau-de-parfum-acqua-lotus-coffret",
    "sources": [
      "molinard"
    ]
  },
  {
    "brand": "Molinard",
    "name": "Eau de Parfum Ambre",
    "release_year": null,
    "concentration": "edp",
    "fragrance_family": null,
    "gender": "unisex",
    "top_notes": [],
    "heart_notes": [],
    "base_notes": [],
    "top_accords": [],
    "accord_intensity": {},
    "community_longevity": null,
    "community_sillage": null,
    "community_projection": null,
    "compliment_score": null,
    "versatility_score": null,
    "office_safe_score": null,
    "price_tier": null,
    "retail_msrp_usd_cents": null,
    "prices": [],
    "image_url": "https://cdn.shopify.com/s/files/1/0722/1421/7014/files/8136613822774-95f7151ce984357c8bef65fd592afab59fbeb328.jpg?v=1768397686",
    "source": "molinard",
    "source_url": "https://www.molinard.com/products/eau-de-parfum-ambre",
    "sources": [
      "molinard"
    ]
  },
  {
    "brand": "Molinard",
    "name": "Eau de Parfum Ambré Lumière",
    "release_year": null,
    "concentration": "edp",
    "fragrance_family": null,
    "gender": "unisex",
    "top_notes": [],
    "heart_notes": [],
    "base_notes": [],
    "top_accords": [],
    "accord_intensity": {},
    "community_longevity": null,
    "community_sillage": null,
    "community_projection": null,
    "compliment_score": null,
    "versatility_score": null,
    "office_safe_score": null,
    "price_tier": null,
    "retail_msrp_usd_cents": null,
    "prices": [],
    "image_url": "https://cdn.shopify.com/s/files/1/0722/1421/7014/files/8659903283535-8bc6277fcb993515bee6dafca5000ca2111b3281.jpg?v=1768397594",
    "source": "molinard",
    "source_url": "https://www.molinard.com/products/eau-de-parfum-ambre-lumiere-coffret",
    "sources": [
      "molinard"
    ]
  },
  {
    "brand": "Molinard",
    "name": "Eau de Parfum Bambou",
    "release_year": null,
    "concentration": "edp",
    "fragrance_family": null,
    "gender": "unisex",
    "top_notes": [],
    "heart_notes": [],
    "base_notes": [],
    "top_accords": [],
    "accord_intensity": {},
    "community_longevity": null,
    "community_sillage": null,
    "community_projection": null,
    "compliment_score": null,
    "versatility_score": null,
    "office_safe_score": null,
    "price_tier": null,
    "retail_msrp_usd_cents": null,
    "prices": [],
    "image_url": "https://cdn.shopify.com/s/files/1/0722/1421/7014/files/8516129620303-52301f1a2e7544a0f11ad7ccdada266ed6b39798.png?v=1768397788",
    "source": "molinard",
    "source_url": "https://www.molinard.com/products/eau-de-parfum-bambou",
    "sources": [
      "molinard"
    ]
  },
  {
    "brand": "Molinard",
    "name": "Eau de Parfum Campus",
    "release_year": null,
    "concentration": "edp",
    "fragrance_family": null,
    "gender": "unisex",
    "top_notes": [],
    "heart_notes": [],
    "base_notes": [],
    "top_accords": [],
    "accord_intensity": {},
    "community_longevity": null,
    "community_sillage": null,
    "community_projection": null,
    "compliment_score": null,
    "versatility_score": null,
    "office_safe_score": null,
    "price_tier": null,
    "retail_msrp_usd_cents": null,
    "prices": [],
    "image_url": "https://cdn.shopify.com/s/files/1/0722/1421/7014/files/8136126398774-8ff6963185fc8bee4509adad119f7c5819bd9e15.jpg?v=1768397565",
    "source": "molinard",
    "source_url": "https://www.molinard.com/products/campus",
    "sources": [
      "molinard"
    ]
  },
  {
    "brand": "Molinard",
    "name": "Eau de Parfum Cher Wood",
    "release_year": null,
    "concentration": "edp",
    "fragrance_family": null,
    "gender": "unisex",
    "top_notes": [],
    "heart_notes": [],
    "base_notes": [],
    "top_accords": [],
    "accord_intensity": {},
    "community_longevity": null,
    "community_sillage": null,
    "community_projection": null,
    "compliment_score": null,
    "versatility_score": null,
    "office_safe_score": null,
    "price_tier": null,
    "retail_msrp_usd_cents": null,
    "prices": [],
    "image_url": "https://cdn.shopify.com/s/files/1/0722/1421/7014/files/8660086030671-9404e2f742fc8f269bbcc75a4af85796ee6c94b7.jpg?v=1768397636",
    "source": "molinard",
    "source_url": "https://www.molinard.com/products/eau-de-parfum-cher-wood-coffret",
    "sources": [
      "molinard"
    ]
  },
  {
    "brand": "Molinard",
    "name": "Eau de Parfum Chypre Charnel",
    "release_year": null,
    "concentration": "edp",
    "fragrance_family": null,
    "gender": "unisex",
    "top_notes": [],
    "heart_notes": [],
    "base_notes": [],
    "top_accords": [],
    "accord_intensity": {},
    "community_longevity": null,
    "community_sillage": null,
    "community_projection": null,
    "compliment_score": null,
    "versatility_score": null,
    "office_safe_score": null,
    "price_tier": null,
    "retail_msrp_usd_cents": null,
    "prices": [],
    "image_url": "https://cdn.shopify.com/s/files/1/0722/1421/7014/files/8163298836790-a30f6ae4fc359efc5271abcd85e64323a620cd41.jpg?v=1768397800",
    "source": "molinard",
    "source_url": "https://www.molinard.com/products/eau-de-parfum-chypre-charnel",
    "sources": [
      "molinard"
    ]
  },
  {
    "brand": "Molinard",
    "name": "Eau de Parfum Citrus Noir",
    "release_year": null,
    "concentration": "edp",
    "fragrance_family": null,
    "gender": "unisex",
    "top_notes": [],
    "heart_notes": [],
    "base_notes": [],
    "top_accords": [],
    "accord_intensity": {},
    "community_longevity": null,
    "community_sillage": null,
    "community_projection": null,
    "compliment_score": null,
    "versatility_score": null,
    "office_safe_score": null,
    "price_tier": null,
    "retail_msrp_usd_cents": null,
    "prices": [],
    "image_url": "https://cdn.shopify.com/s/files/1/0722/1421/7014/files/8136412266806-e31ced0f0665f0a8efdf48637999612d60e2c20c.jpg?v=1768397776",
    "source": "molinard",
    "source_url": "https://www.molinard.com/products/eau-de-parfum-citrus-noir",
    "sources": [
      "molinard"
    ]
  },
  {
    "brand": "Molinard",
    "name": "Eau de Parfum Cuir",
    "release_year": null,
    "concentration": "edp",
    "fragrance_family": null,
    "gender": "unisex",
    "top_notes": [],
    "heart_notes": [],
    "base_notes": [],
    "top_accords": [],
    "accord_intensity": {},
    "community_longevity": null,
    "community_sillage": null,
    "community_projection": null,
    "compliment_score": null,
    "versatility_score": null,
    "office_safe_score": null,
    "price_tier": null,
    "retail_msrp_usd_cents": null,
    "prices": [],
    "image_url": "https://cdn.shopify.com/s/files/1/0722/1421/7014/files/8136622309686-8b18f7cdce91e8f02cd01fd5a7da2f9688bf1e5a.jpg?v=1768397747",
    "source": "molinard",
    "source_url": "https://www.molinard.com/products/eau-de-parfum-cuir",
    "sources": [
      "molinard"
    ]
  },
  {
    "brand": "Molinard",
    "name": "Eau de Parfum Figue",
    "release_year": null,
    "concentration": "edp",
    "fragrance_family": null,
    "gender": "unisex",
    "top_notes": [],
    "heart_notes": [],
    "base_notes": [],
    "top_accords": [],
    "accord_intensity": {},
    "community_longevity": null,
    "community_sillage": null,
    "community_projection": null,
    "compliment_score": null,
    "versatility_score": null,
    "office_safe_score": null,
    "price_tier": null,
    "retail_msrp_usd_cents": null,
    "prices": [],
    "image_url": "https://cdn.shopify.com/s/files/1/0722/1421/7014/files/8136624472374-25a80ba041d81fef39d06db880ec83467c07edc9.jpg?v=1768397697",
    "source": "molinard",
    "source_url": "https://www.molinard.com/products/figue",
    "sources": [
      "molinard"
    ]
  },
  {
    "brand": "Molinard",
    "name": "Eau de Parfum Fleur d'Oranger",
    "release_year": null,
    "concentration": "edp",
    "fragrance_family": null,
    "gender": "unisex",
    "top_notes": [],
    "heart_notes": [],
    "base_notes": [],
    "top_accords": [],
    "accord_intensity": {},
    "community_longevity": null,
    "community_sillage": null,
    "community_projection": null,
    "compliment_score": null,
    "versatility_score": null,
    "office_safe_score": null,
    "price_tier": null,
    "retail_msrp_usd_cents": null,
    "prices": [],
    "image_url": "https://cdn.shopify.com/s/files/1/0722/1421/7014/files/8136626798902-e9798a45bcd67e109a9e4e3b2fad74930d31a4de.jpg?v=1768397703",
    "source": "molinard",
    "source_url": "https://www.molinard.com/products/fleur-doranger",
    "sources": [
      "molinard"
    ]
  },
  {
    "brand": "Molinard",
    "name": "Eau de Parfum Gingembre",
    "release_year": null,
    "concentration": "edp",
    "fragrance_family": null,
    "gender": "unisex",
    "top_notes": [],
    "heart_notes": [],
    "base_notes": [],
    "top_accords": [],
    "accord_intensity": {},
    "community_longevity": null,
    "community_sillage": null,
    "community_projection": null,
    "compliment_score": null,
    "versatility_score": null,
    "office_safe_score": null,
    "price_tier": null,
    "retail_msrp_usd_cents": null,
    "prices": [],
    "image_url": "https://cdn.shopify.com/s/files/1/0722/1421/7014/files/8136413511990-1e7719ad982c8f895d1789f85769a29248e75cfb.jpg?v=1768397764",
    "source": "molinard",
    "source_url": "https://www.molinard.com/products/gingembre",
    "sources": [
      "molinard"
    ]
  },
  {
    "brand": "Molinard",
    "name": "Eau de Parfum Habanita",
    "release_year": null,
    "concentration": "edp",
    "fragrance_family": null,
    "gender": "unisex",
    "top_notes": [],
    "heart_notes": [],
    "base_notes": [],
    "top_accords": [],
    "accord_intensity": {},
    "community_longevity": null,
    "community_sillage": null,
    "community_projection": null,
    "compliment_score": null,
    "versatility_score": null,
    "office_safe_score": null,
    "price_tier": null,
    "retail_msrp_usd_cents": null,
    "prices": [],
    "image_url": "https://cdn.shopify.com/s/files/1/0722/1421/7014/files/8136208089398-b71a46c86a8374c916ce9fa23ae77876f2af141f.jpg?v=1768397507",
    "source": "molinard",
    "source_url": "https://www.molinard.com/products/habanita",
    "sources": [
      "molinard"
    ]
  },
  {
    "brand": "Molinard",
    "name": "Eau de Parfum Habanita 30ml",
    "release_year": null,
    "concentration": "edp",
    "fragrance_family": null,
    "gender": "unisex",
    "top_notes": [],
    "heart_notes": [],
    "base_notes": [],
    "top_accords": [],
    "accord_intensity": {},
    "community_longevity": null,
    "community_sillage": null,
    "community_projection": null,
    "compliment_score": null,
    "versatility_score": null,
    "office_safe_score": null,
    "price_tier": null,
    "retail_msrp_usd_cents": null,
    "prices": [],
    "image_url": "https://cdn.shopify.com/s/files/1/0722/1421/7014/files/8136210645302-385b040912e011c03100e79574860a9e2b3195f9.jpg?v=1768397513",
    "source": "molinard",
    "source_url": "https://www.molinard.com/products/habanita-1",
    "sources": [
      "molinard"
    ]
  },
  {
    "brand": "Molinard",
    "name": "Eau de Parfum Habanita L'Esprit",
    "release_year": null,
    "concentration": "edp",
    "fragrance_family": null,
    "gender": "unisex",
    "top_notes": [],
    "heart_notes": [],
    "base_notes": [],
    "top_accords": [],
    "accord_intensity": {},
    "community_longevity": null,
    "community_sillage": null,
    "community_projection": null,
    "compliment_score": null,
    "versatility_score": null,
    "office_safe_score": null,
    "price_tier": null,
    "retail_msrp_usd_cents": null,
    "prices": [],
    "image_url": "https://cdn.shopify.com/s/files/1/0722/1421/7014/files/8136223850806-d07487226301fdbd5aebf4d2ebc750dfdbd8b984.jpg?v=1768397524",
    "source": "molinard",
    "source_url": "https://www.molinard.com/products/habanita-lesprit",
    "sources": [
      "molinard"
    ]
  },
  {
    "brand": "Molinard",
    "name": "Eau de Parfum Îles d'Or",
    "release_year": null,
    "concentration": "edp",
    "fragrance_family": null,
    "gender": "unisex",
    "top_notes": [],
    "heart_notes": [],
    "base_notes": [],
    "top_accords": [],
    "accord_intensity": {},
    "community_longevity": null,
    "community_sillage": null,
    "community_projection": null,
    "compliment_score": null,
    "versatility_score": null,
    "office_safe_score": null,
    "price_tier": null,
    "retail_msrp_usd_cents": null,
    "prices": [],
    "image_url": "https://cdn.shopify.com/s/files/1/0722/1421/7014/files/8109749469494-5b683250c0870965e6bf87e8c87b2acd329d690c.jpg?v=1768397582",
    "source": "molinard",
    "source_url": "https://www.molinard.com/products/iles-dor",
    "sources": [
      "molinard"
    ]
  },
  {
    "brand": "Molinard",
    "name": "Eau de Parfum Iris",
    "release_year": null,
    "concentration": "edp",
    "fragrance_family": null,
    "gender": "unisex",
    "top_notes": [],
    "heart_notes": [],
    "base_notes": [],
    "top_accords": [],
    "accord_intensity": {},
    "community_longevity": null,
    "community_sillage": null,
    "community_projection": null,
    "compliment_score": null,
    "versatility_score": null,
    "office_safe_score": null,
    "price_tier": null,
    "retail_msrp_usd_cents": null,
    "prices": [],
    "image_url": "https://cdn.shopify.com/s/files/1/0722/1421/7014/files/8972846170447-09284b3e103d121327e8e3891dfba9c6987a938d.png?v=1768469428",
    "source": "molinard",
    "source_url": "https://www.molinard.com/products/eau-de-parfum-iris",
    "sources": [
      "molinard"
    ]
  },
  {
    "brand": "Molinard",
    "name": "Eau de Parfum Iris Ardent",
    "release_year": null,
    "concentration": "edp",
    "fragrance_family": null,
    "gender": "unisex",
    "top_notes": [],
    "heart_notes": [],
    "base_notes": [],
    "top_accords": [],
    "accord_intensity": {},
    "community_longevity": null,
    "community_sillage": null,
    "community_projection": null,
    "compliment_score": null,
    "versatility_score": null,
    "office_safe_score": null,
    "price_tier": null,
    "retail_msrp_usd_cents": null,
    "prices": [],
    "image_url": "https://cdn.shopify.com/s/files/1/0722/1421/7014/files/9421097533775-ceb96fd5ec33e27aa5a4e0d1b8a56319181bf250.png?v=1768471312",
    "source": "molinard",
    "source_url": "https://www.molinard.com/products/eau-de-parfum-iris-ardent",
    "sources": [
      "molinard"
    ]
  },
  {
    "brand": "Molinard",
    "name": "Eau de Parfum Jasmin",
    "release_year": null,
    "concentration": "edp",
    "fragrance_family": null,
    "gender": "unisex",
    "top_notes": [],
    "heart_notes": [],
    "base_notes": [],
    "top_accords": [],
    "accord_intensity": {},
    "community_longevity": null,
    "community_sillage": null,
    "community_projection": null,
    "compliment_score": null,
    "versatility_score": null,
    "office_safe_score": null,
    "price_tier": null,
    "retail_msrp_usd_cents": null,
    "prices": [],
    "image_url": "https://cdn.shopify.com/s/files/1/0722/1421/7014/files/8136629322038-56f9bd657492ebd8c24a0cbf205e8a0bcef26f50.jpg?v=1768397734",
    "source": "molinard",
    "source_url": "https://www.molinard.com/products/jasmin",
    "sources": [
      "molinard"
    ]
  },
  {
    "brand": "Molinard",
    "name": "Eau de Parfum Lavande",
    "release_year": null,
    "concentration": "edp",
    "fragrance_family": null,
    "gender": "unisex",
    "top_notes": [],
    "heart_notes": [],
    "base_notes": [],
    "top_accords": [],
    "accord_intensity": {},
    "community_longevity": null,
    "community_sillage": null,
    "community_projection": null,
    "compliment_score": null,
    "versatility_score": null,
    "office_safe_score": null,
    "price_tier": null,
    "retail_msrp_usd_cents": null,
    "prices": [],
    "image_url": "https://cdn.shopify.com/s/files/1/0722/1421/7014/files/8312995447094-219380441d8ac30c31e5cd5f1c7646ef9299a360.jpg?v=1768397709",
    "source": "molinard",
    "source_url": "https://www.molinard.com/products/lavande-1",
    "sources": [
      "molinard"
    ]
  },
  {
    "brand": "Molinard",
    "name": "Eau de Parfum Madrigal",
    "release_year": null,
    "concentration": "edp",
    "fragrance_family": null,
    "gender": "unisex",
    "top_notes": [],
    "heart_notes": [],
    "base_notes": [],
    "top_accords": [],
    "accord_intensity": {},
    "community_longevity": null,
    "community_sillage": null,
    "community_projection": null,
    "compliment_score": null,
    "versatility_score": null,
    "office_safe_score": null,
    "price_tier": null,
    "retail_msrp_usd_cents": null,
    "prices": [],
    "image_url": "https://cdn.shopify.com/s/files/1/0722/1421/7014/files/8136164311350-1b9201c447eb1a66115ee45d13f4af95f9caae0d.jpg?v=1768397554",
    "source": "molinard",
    "source_url": "https://www.molinard.com/products/madrigal",
    "sources": [
      "molinard"
    ]
  },
  {
    "brand": "Molinard",
    "name": "Eau de Parfum Méditerranée",
    "release_year": null,
    "concentration": "edp",
    "fragrance_family": null,
    "gender": "unisex",
    "top_notes": [],
    "heart_notes": [],
    "base_notes": [],
    "top_accords": [],
    "accord_intensity": {},
    "community_longevity": null,
    "community_sillage": null,
    "community_projection": null,
    "compliment_score": null,
    "versatility_score": null,
    "office_safe_score": null,
    "price_tier": null,
    "retail_msrp_usd_cents": null,
    "prices": [],
    "image_url": "https://cdn.shopify.com/s/files/1/0722/1421/7014/files/8136415707446-6b8d248da8c605090bc356bc1a99139cb548853e.jpg?v=1768397770",
    "source": "molinard",
    "source_url": "https://www.molinard.com/products/mediterrannee",
    "sources": [
      "molinard"
    ]
  },
  {
    "brand": "Molinard",
    "name": "Eau de Parfum Miréa",
    "release_year": null,
    "concentration": "edp",
    "fragrance_family": null,
    "gender": "unisex",
    "top_notes": [],
    "heart_notes": [],
    "base_notes": [],
    "top_accords": [],
    "accord_intensity": {},
    "community_longevity": null,
    "community_sillage": null,
    "community_projection": null,
    "compliment_score": null,
    "versatility_score": null,
    "office_safe_score": null,
    "price_tier": null,
    "retail_msrp_usd_cents": null,
    "prices": [],
    "image_url": "https://cdn.shopify.com/s/files/1/0722/1421/7014/files/8136063287606-d11202f1ef8b396d84d5a540f9ddd7ea67910663.jpg?v=1768397571",
    "source": "molinard",
    "source_url": "https://www.molinard.com/products/mirea",
    "sources": [
      "molinard"
    ]
  },
  {
    "brand": "Molinard",
    "name": "Eau de Parfum Muguet",
    "release_year": null,
    "concentration": "edp",
    "fragrance_family": null,
    "gender": "unisex",
    "top_notes": [],
    "heart_notes": [],
    "base_notes": [],
    "top_accords": [],
    "accord_intensity": {},
    "community_longevity": null,
    "community_sillage": null,
    "community_projection": null,
    "compliment_score": null,
    "versatility_score": null,
    "office_safe_score": null,
    "price_tier": null,
    "retail_msrp_usd_cents": null,
    "prices": [],
    "image_url": "https://cdn.shopify.com/s/files/1/0722/1421/7014/files/8307329237302-52b1d117902e7f4b61e3636650515a4a71bdc576.jpg?v=1768397753",
    "source": "molinard",
    "source_url": "https://www.molinard.com/products/muguet",
    "sources": [
      "molinard"
    ]
  },
  {
    "brand": "Molinard",
    "name": "Eau de Parfum Musc",
    "release_year": null,
    "concentration": "edp",
    "fragrance_family": null,
    "gender": "unisex",
    "top_notes": [],
    "heart_notes": [],
    "base_notes": [],
    "top_accords": [],
    "accord_intensity": {},
    "community_longevity": null,
    "community_sillage": null,
    "community_projection": null,
    "compliment_score": null,
    "versatility_score": null,
    "office_safe_score": null,
    "price_tier": null,
    "retail_msrp_usd_cents": null,
    "prices": [],
    "image_url": "https://cdn.shopify.com/s/files/1/0722/1421/7014/files/8164406100278-d0be455c7c03883296e9024160d5f0e7b1f3921d.jpg?v=1768397691",
    "source": "molinard",
    "source_url": "https://www.molinard.com/products/musc",
    "sources": [
      "molinard"
    ]
  },
  {
    "brand": "Molinard",
    "name": "Eau de Parfum Nirmala",
    "release_year": null,
    "concentration": "edp",
    "fragrance_family": null,
    "gender": "unisex",
    "top_notes": [],
    "heart_notes": [],
    "base_notes": [],
    "top_accords": [],
    "accord_intensity": {},
    "community_longevity": null,
    "community_sillage": null,
    "community_projection": null,
    "compliment_score": null,
    "versatility_score": null,
    "office_safe_score": null,
    "price_tier": null,
    "retail_msrp_usd_cents": null,
    "prices": [],
    "image_url": "https://cdn.shopify.com/s/files/1/0722/1421/7014/files/8136196096310-7b5ac302638408a0a160a98d256c0f89f3a10474.jpg?v=1768397542",
    "source": "molinard",
    "source_url": "https://www.molinard.com/products/nirmala-1",
    "sources": [
      "molinard"
    ]
  },
  {
    "brand": "Molinard",
    "name": "Eau de Parfum Osmanthus",
    "release_year": null,
    "concentration": "edp",
    "fragrance_family": null,
    "gender": "unisex",
    "top_notes": [],
    "heart_notes": [],
    "base_notes": [],
    "top_accords": [],
    "accord_intensity": {},
    "community_longevity": null,
    "community_sillage": null,
    "community_projection": null,
    "compliment_score": null,
    "versatility_score": null,
    "office_safe_score": null,
    "price_tier": null,
    "retail_msrp_usd_cents": null,
    "prices": [],
    "image_url": "https://cdn.shopify.com/s/files/1/0722/1421/7014/files/8164408492342-44e892631c4cc56fb2560568f3d5ad88db46687f.jpg?v=1768397717",
    "source": "molinard",
    "source_url": "https://www.molinard.com/products/osmanthus",
    "sources": [
      "molinard"
    ]
  },
  {
    "brand": "Molinard",
    "name": "Eau de Parfum Oud Magnétique",
    "release_year": null,
    "concentration": "edp",
    "fragrance_family": null,
    "gender": "unisex",
    "top_notes": [],
    "heart_notes": [],
    "base_notes": [],
    "top_accords": [],
    "accord_intensity": {},
    "community_longevity": null,
    "community_sillage": null,
    "community_projection": null,
    "compliment_score": null,
    "versatility_score": null,
    "office_safe_score": null,
    "price_tier": null,
    "retail_msrp_usd_cents": null,
    "prices": [],
    "image_url": "https://cdn.shopify.com/s/files/1/0722/1421/7014/files/8163486990646-27a448da374e970e28646bff59a76b6ea8eb6037.jpg?v=1768397817",
    "source": "molinard",
    "source_url": "https://www.molinard.com/products/oud-magnetique",
    "sources": [
      "molinard"
    ]
  },
  {
    "brand": "Molinard",
    "name": "Eau de Parfum Patchouli",
    "release_year": null,
    "concentration": "edp",
    "fragrance_family": null,
    "gender": "unisex",
    "top_notes": [],
    "heart_notes": [],
    "base_notes": [],
    "top_accords": [],
    "accord_intensity": {},
    "community_longevity": null,
    "community_sillage": null,
    "community_projection": null,
    "compliment_score": null,
    "versatility_score": null,
    "office_safe_score": null,
    "price_tier": null,
    "retail_msrp_usd_cents": null,
    "prices": [],
    "image_url": "https://cdn.shopify.com/s/files/1/0722/1421/7014/files/8164410196278-3ad55facd4b60399deff9963b5b762609ea86c6f.jpg?v=1768397660",
    "source": "molinard",
    "source_url": "https://www.molinard.com/products/patchouli",
    "sources": [
      "molinard"
    ]
  },
  {
    "brand": "Molinard",
    "name": "Eau de Parfum Patchouli Intense",
    "release_year": null,
    "concentration": "edp",
    "fragrance_family": null,
    "gender": "unisex",
    "top_notes": [],
    "heart_notes": [],
    "base_notes": [],
    "top_accords": [],
    "accord_intensity": {},
    "community_longevity": null,
    "community_sillage": null,
    "community_projection": null,
    "compliment_score": null,
    "versatility_score": null,
    "office_safe_score": null,
    "price_tier": null,
    "retail_msrp_usd_cents": null,
    "prices": [],
    "image_url": "https://cdn.shopify.com/s/files/1/0722/1421/7014/files/8163538010422-eeb54d28abc51da5845b24393f4ef5a97af6c7fd.jpg?v=1768397794",
    "source": "molinard",
    "source_url": "https://www.molinard.com/products/patchouli-intense",
    "sources": [
      "molinard"
    ]
  },
  {
    "brand": "Molinard",
    "name": "Eau de Parfum Rose",
    "release_year": null,
    "concentration": "edp",
    "fragrance_family": null,
    "gender": "unisex",
    "top_notes": [],
    "heart_notes": [],
    "base_notes": [],
    "top_accords": [],
    "accord_intensity": {},
    "community_longevity": null,
    "community_sillage": null,
    "community_projection": null,
    "compliment_score": null,
    "versatility_score": null,
    "office_safe_score": null,
    "price_tier": null,
    "retail_msrp_usd_cents": null,
    "prices": [],
    "image_url": "https://cdn.shopify.com/s/files/1/0722/1421/7014/files/8164410720566-4479bcc2e4a38663554b3842f3a1ae4bd2f4943c.jpg?v=1768397728",
    "source": "molinard",
    "source_url": "https://www.molinard.com/products/rose",
    "sources": [
      "molinard"
    ]
  },
  {
    "brand": "Molinard",
    "name": "Eau de Parfum Rose Émois",
    "release_year": null,
    "concentration": "edp",
    "fragrance_family": null,
    "gender": "unisex",
    "top_notes": [],
    "heart_notes": [],
    "base_notes": [],
    "top_accords": [],
    "accord_intensity": {},
    "community_longevity": null,
    "community_sillage": null,
    "community_projection": null,
    "compliment_score": null,
    "versatility_score": null,
    "office_safe_score": null,
    "price_tier": null,
    "retail_msrp_usd_cents": null,
    "prices": [],
    "image_url": "https://cdn.shopify.com/s/files/1/0722/1421/7014/files/8660103135567-bea69f97f346c240892a7c2b1508b5d38795feed.jpg?v=1768397607",
    "source": "molinard",
    "source_url": "https://www.molinard.com/products/eau-de-parfum-rose-emois-coffret",
    "sources": [
      "molinard"
    ]
  },
  {
    "brand": "Molinard",
    "name": "Eau de Parfum Rose Turkia",
    "release_year": null,
    "concentration": "edp",
    "fragrance_family": null,
    "gender": "unisex",
    "top_notes": [],
    "heart_notes": [],
    "base_notes": [],
    "top_accords": [],
    "accord_intensity": {},
    "community_longevity": null,
    "community_sillage": null,
    "community_projection": null,
    "compliment_score": null,
    "versatility_score": null,
    "office_safe_score": null,
    "price_tier": null,
    "retail_msrp_usd_cents": null,
    "prices": [],
    "image_url": "https://cdn.shopify.com/s/files/1/0722/1421/7014/files/8163541909814-87ad58de257e1187e3452d41acee75c6e745d310.jpg?v=1768397811",
    "source": "molinard",
    "source_url": "https://www.molinard.com/products/rose-turkia",
    "sources": [
      "molinard"
    ]
  },
  {
    "brand": "Molinard",
    "name": "Eau de Parfum Santal Insolent",
    "release_year": null,
    "concentration": "edp",
    "fragrance_family": null,
    "gender": "unisex",
    "top_notes": [],
    "heart_notes": [],
    "base_notes": [],
    "top_accords": [],
    "accord_intensity": {},
    "community_longevity": null,
    "community_sillage": null,
    "community_projection": null,
    "compliment_score": null,
    "versatility_score": null,
    "office_safe_score": null,
    "price_tier": null,
    "retail_msrp_usd_cents": null,
    "prices": [],
    "image_url": "https://cdn.shopify.com/s/files/1/0722/1421/7014/files/8163553050934-91bfc0fa54e1af8c240143048f990349bc5a0260.jpg?v=1768397823",
    "source": "molinard",
    "source_url": "https://www.molinard.com/products/santal-insolent",
    "sources": [
      "molinard"
    ]
  },
  {
    "brand": "Molinard",
    "name": "Eau de Parfum Secret Sucré",
    "release_year": null,
    "concentration": "edp",
    "fragrance_family": null,
    "gender": "unisex",
    "top_notes": [],
    "heart_notes": [],
    "base_notes": [],
    "top_accords": [],
    "accord_intensity": {},
    "community_longevity": null,
    "community_sillage": null,
    "community_projection": null,
    "compliment_score": null,
    "versatility_score": null,
    "office_safe_score": null,
    "price_tier": null,
    "retail_msrp_usd_cents": null,
    "prices": [],
    "image_url": "https://cdn.shopify.com/s/files/1/0722/1421/7014/files/8660110606671-602abb272db8f1abc2b6c872dd623975459cf7ab.jpg?v=1768397625",
    "source": "molinard",
    "source_url": "https://www.molinard.com/products/eau-de-parfum-secret-sucre-coffret",
    "sources": [
      "molinard"
    ]
  },
  {
    "brand": "Molinard",
    "name": "Eau de Parfum Tubéreuse Vertigineuse",
    "release_year": null,
    "concentration": "edp",
    "fragrance_family": null,
    "gender": "unisex",
    "top_notes": [],
    "heart_notes": [],
    "base_notes": [],
    "top_accords": [],
    "accord_intensity": {},
    "community_longevity": null,
    "community_sillage": null,
    "community_projection": null,
    "compliment_score": null,
    "versatility_score": null,
    "office_safe_score": null,
    "price_tier": null,
    "retail_msrp_usd_cents": null,
    "prices": [],
    "image_url": "https://cdn.shopify.com/s/files/1/0722/1421/7014/files/8163556000054-79f8718a7c06f9fd6892816d20fa58cd64340886.jpg?v=1768397806",
    "source": "molinard",
    "source_url": "https://www.molinard.com/products/tubereuse-vertigineuse",
    "sources": [
      "molinard"
    ]
  },
  {
    "brand": "Molinard",
    "name": "Eau de Parfum Vanille",
    "release_year": null,
    "concentration": "edp",
    "fragrance_family": null,
    "gender": "unisex",
    "top_notes": [],
    "heart_notes": [],
    "base_notes": [],
    "top_accords": [],
    "accord_intensity": {},
    "community_longevity": null,
    "community_sillage": null,
    "community_projection": null,
    "compliment_score": null,
    "versatility_score": null,
    "office_safe_score": null,
    "price_tier": null,
    "retail_msrp_usd_cents": null,
    "prices": [],
    "image_url": "https://cdn.shopify.com/s/files/1/0722/1421/7014/files/8164411408694-40de35def396d78fff5d8a0afb9db653dc613464.jpg?v=1768397666",
    "source": "molinard",
    "source_url": "https://www.molinard.com/products/vanille",
    "sources": [
      "molinard"
    ]
  },
  {
    "brand": "Molinard",
    "name": "Eau de Parfum Vanille Fruitée",
    "release_year": null,
    "concentration": "edp",
    "fragrance_family": null,
    "gender": "unisex",
    "top_notes": [],
    "heart_notes": [],
    "base_notes": [],
    "top_accords": [],
    "accord_intensity": {},
    "community_longevity": null,
    "community_sillage": null,
    "community_projection": null,
    "compliment_score": null,
    "versatility_score": null,
    "office_safe_score": null,
    "price_tier": null,
    "retail_msrp_usd_cents": null,
    "prices": [],
    "image_url": "https://cdn.shopify.com/s/files/1/0722/1421/7014/files/8164413047094-ea22369bf7c0bac7d31dee71fdf2c86bc398ecf6.jpg?v=1768397740",
    "source": "molinard",
    "source_url": "https://www.molinard.com/products/vanille-fruitee",
    "sources": [
      "molinard"
    ]
  },
  {
    "brand": "Molinard",
    "name": "Eau de Parfum Vanille Patchouli",
    "release_year": null,
    "concentration": "edp",
    "fragrance_family": null,
    "gender": "unisex",
    "top_notes": [],
    "heart_notes": [],
    "base_notes": [],
    "top_accords": [],
    "accord_intensity": {},
    "community_longevity": null,
    "community_sillage": null,
    "community_projection": null,
    "compliment_score": null,
    "versatility_score": null,
    "office_safe_score": null,
    "price_tier": null,
    "retail_msrp_usd_cents": null,
    "prices": [],
    "image_url": "https://cdn.shopify.com/s/files/1/0722/1421/7014/files/8164456825142-89f9e766d3d66b7111e0219acd55b25fd4b78f5d.jpg?v=1768397673",
    "source": "molinard",
    "source_url": "https://www.molinard.com/products/vanille-patchouli",
    "sources": [
      "molinard"
    ]
  },
  {
    "brand": "Molinard",
    "name": "Eau de Parfum Vents et Marées",
    "release_year": null,
    "concentration": "edp",
    "fragrance_family": null,
    "gender": "unisex",
    "top_notes": [],
    "heart_notes": [],
    "base_notes": [],
    "top_accords": [],
    "accord_intensity": {},
    "community_longevity": null,
    "community_sillage": null,
    "community_projection": null,
    "compliment_score": null,
    "versatility_score": null,
    "office_safe_score": null,
    "price_tier": null,
    "retail_msrp_usd_cents": null,
    "prices": [],
    "image_url": "https://cdn.shopify.com/s/files/1/0722/1421/7014/files/8136103887158-1acf8a98091a9f1354111ef328d9ca0dbb52e78a.jpg?v=1768397577",
    "source": "molinard",
    "source_url": "https://www.molinard.com/products/vents-marees",
    "sources": [
      "molinard"
    ]
  },
  {
    "brand": "Molinard",
    "name": "Eau de Parfum Vétiver",
    "release_year": null,
    "concentration": "edp",
    "fragrance_family": null,
    "gender": "unisex",
    "top_notes": [],
    "heart_notes": [],
    "base_notes": [],
    "top_accords": [],
    "accord_intensity": {},
    "community_longevity": null,
    "community_sillage": null,
    "community_projection": null,
    "compliment_score": null,
    "versatility_score": null,
    "office_safe_score": null,
    "price_tier": null,
    "retail_msrp_usd_cents": null,
    "prices": [],
    "image_url": "https://cdn.shopify.com/s/files/1/0722/1421/7014/files/8164459905334-5d40108a9af8ed97ef1e83b76ed9ee076a925402.jpg?v=1768397723",
    "source": "molinard",
    "source_url": "https://www.molinard.com/products/vetiver",
    "sources": [
      "molinard"
    ]
  },
  {
    "brand": "Molinard",
    "name": "Eau de Parfum Violette",
    "release_year": null,
    "concentration": "edp",
    "fragrance_family": null,
    "gender": "unisex",
    "top_notes": [],
    "heart_notes": [],
    "base_notes": [],
    "top_accords": [],
    "accord_intensity": {},
    "community_longevity": null,
    "community_sillage": null,
    "community_projection": null,
    "compliment_score": null,
    "versatility_score": null,
    "office_safe_score": null,
    "price_tier": null,
    "retail_msrp_usd_cents": null,
    "prices": [],
    "image_url": "https://cdn.shopify.com/s/files/1/0722/1421/7014/files/8164461642038-fccb9d08313c77703d74a8343e821e0285983c6f.jpg?v=1768397680",
    "source": "molinard",
    "source_url": "https://www.molinard.com/products/violette",
    "sources": [
      "molinard"
    ]
  },
  {
    "brand": "Molinard",
    "name": "Eau de Toilette Bel Air",
    "release_year": null,
    "concentration": "edt",
    "fragrance_family": null,
    "gender": "unisex",
    "top_notes": [],
    "heart_notes": [],
    "base_notes": [],
    "top_accords": [],
    "accord_intensity": {},
    "community_longevity": null,
    "community_sillage": null,
    "community_projection": null,
    "compliment_score": null,
    "versatility_score": null,
    "office_safe_score": null,
    "price_tier": null,
    "retail_msrp_usd_cents": null,
    "prices": [],
    "image_url": "https://cdn.shopify.com/s/files/1/0722/1421/7014/files/8136190427446-692109ba8c1821e9ca49367d408dc9c877089705.jpg?v=1768397536",
    "source": "molinard",
    "source_url": "https://www.molinard.com/products/bel-air",
    "sources": [
      "molinard"
    ]
  },
  {
    "brand": "Molinard",
    "name": "Eau de Toilette Le Rêve Nirmala",
    "release_year": null,
    "concentration": "edt",
    "fragrance_family": null,
    "gender": "unisex",
    "top_notes": [],
    "heart_notes": [],
    "base_notes": [],
    "top_accords": [],
    "accord_intensity": {},
    "community_longevity": null,
    "community_sillage": null,
    "community_projection": null,
    "compliment_score": null,
    "versatility_score": null,
    "office_safe_score": null,
    "price_tier": null,
    "retail_msrp_usd_cents": null,
    "prices": [],
    "image_url": "https://cdn.shopify.com/s/files/1/0722/1421/7014/files/8136192983350-d394423828afb319ede627d525b823988a7b4763.jpg?v=1768397548",
    "source": "molinard",
    "source_url": "https://www.molinard.com/products/nirmala",
    "sources": [
      "molinard"
    ]
  },
  {
    "brand": "Molinard",
    "name": "Eau de Toilette Molinard de Molinard",
    "release_year": null,
    "concentration": "edt",
    "fragrance_family": null,
    "gender": "unisex",
    "top_notes": [],
    "heart_notes": [],
    "base_notes": [],
    "top_accords": [],
    "accord_intensity": {},
    "community_longevity": null,
    "community_sillage": null,
    "community_projection": null,
    "compliment_score": null,
    "versatility_score": null,
    "office_safe_score": null,
    "price_tier": null,
    "retail_msrp_usd_cents": null,
    "prices": [],
    "image_url": "https://cdn.shopify.com/s/files/1/0722/1421/7014/files/8136187740470-3737d6c031ff9ffa202dca04b71b6e8d63af7daa.jpg?v=1768397530",
    "source": "molinard",
    "source_url": "https://www.molinard.com/products/molinard-de-molinard",
    "sources": [
      "molinard"
    ]
  },
  {
    "brand": "Molinard",
    "name": "Échantillon Iris Ardent",
    "release_year": null,
    "concentration": "edp",
    "fragrance_family": null,
    "gender": "unisex",
    "top_notes": [],
    "heart_notes": [],
    "base_notes": [],
    "top_accords": [],
    "accord_intensity": {},
    "community_longevity": null,
    "community_sillage": null,
    "community_projection": null,
    "compliment_score": null,
    "versatility_score": null,
    "office_safe_score": null,
    "price_tier": null,
    "retail_msrp_usd_cents": null,
    "prices": [],
    "image_url": null,
    "source": "molinard",
    "source_url": "https://www.molinard.com/products/iris-ardent-edp-1ml",
    "sources": [
      "molinard"
    ]
  },
  {
    "brand": "Molinard",
    "name": "Échantillon MM",
    "release_year": null,
    "concentration": "parfum",
    "fragrance_family": null,
    "gender": "unisex",
    "top_notes": [],
    "heart_notes": [],
    "base_notes": [],
    "top_accords": [],
    "accord_intensity": {},
    "community_longevity": null,
    "community_sillage": null,
    "community_projection": null,
    "compliment_score": null,
    "versatility_score": null,
    "office_safe_score": null,
    "price_tier": null,
    "retail_msrp_usd_cents": null,
    "prices": [],
    "image_url": "https://cdn.shopify.com/s/files/1/0722/1421/7014/files/8517455905103-6624fb360dc5393490e7cd9c4b208c06f4957905.png?v=1769169458",
    "source": "molinard",
    "source_url": "https://www.molinard.com/products/copie-de-eau-de-parfum-mm",
    "sources": [
      "molinard"
    ]
  },
  {
    "brand": "Molinard",
    "name": "Échantillon Tubéreuse Vertigineuse",
    "release_year": null,
    "concentration": "edp",
    "fragrance_family": null,
    "gender": "unisex",
    "top_notes": [],
    "heart_notes": [],
    "base_notes": [],
    "top_accords": [],
    "accord_intensity": {},
    "community_longevity": null,
    "community_sillage": null,
    "community_projection": null,
    "compliment_score": null,
    "versatility_score": null,
    "office_safe_score": null,
    "price_tier": null,
    "retail_msrp_usd_cents": null,
    "prices": [],
    "image_url": "https://cdn.shopify.com/s/files/1/0722/1421/7014/files/9610074915151-93e7eb88c4e5fe2e42a02eba43daaf79bbdbacdd.png?v=1769167328",
    "source": "molinard",
    "source_url": "https://www.molinard.com/products/tubereuse-vertigineuse-edp-1ml",
    "sources": [
      "molinard"
    ]
  },
  {
    "brand": "Molinard",
    "name": "Étui Roll-on en cuir Bleu Foncé",
    "release_year": null,
    "concentration": "edp",
    "fragrance_family": null,
    "gender": "unisex",
    "top_notes": [],
    "heart_notes": [],
    "base_notes": [],
    "top_accords": [],
    "accord_intensity": {},
    "community_longevity": null,
    "community_sillage": null,
    "community_projection": null,
    "compliment_score": null,
    "versatility_score": null,
    "office_safe_score": null,
    "price_tier": null,
    "retail_msrp_usd_cents": null,
    "prices": [],
    "image_url": "https://cdn.shopify.com/s/files/1/0722/1421/7014/files/15202351939919-aefa633359d14f21e050d7abd8c53bdd07ec85b8_a5e81029-4614-4352-b96b-5bbaff664d06.png?v=1768221137",
    "source": "molinard",
    "source_url": "https://www.molinard.com/products/etui-cuir-roll-on-bleu-fonce",
    "sources": [
      "molinard"
    ]
  },
  {
    "brand": "Molinard",
    "name": "Étui Roll-on en cuir Kaki Foncé",
    "release_year": null,
    "concentration": "edp",
    "fragrance_family": null,
    "gender": "unisex",
    "top_notes": [],
    "heart_notes": [],
    "base_notes": [],
    "top_accords": [],
    "accord_intensity": {},
    "community_longevity": null,
    "community_sillage": null,
    "community_projection": null,
    "compliment_score": null,
    "versatility_score": null,
    "office_safe_score": null,
    "price_tier": null,
    "retail_msrp_usd_cents": null,
    "prices": [],
    "image_url": "https://cdn.shopify.com/s/files/1/0722/1421/7014/files/15604017529167-8d6fce361a4f7001234c55457026f3854e384cc4_c1f0255d-61f7-42cc-99d6-8c7c37b9d10b.png?v=1768221142",
    "source": "molinard",
    "source_url": "https://www.molinard.com/products/etui-cuir-roll-on-kaki-fonce",
    "sources": [
      "molinard"
    ]
  },
  {
    "brand": "Molinard",
    "name": "Habanita La Cologne",
    "release_year": null,
    "concentration": "cologne",
    "fragrance_family": null,
    "gender": "unisex",
    "top_notes": [],
    "heart_notes": [],
    "base_notes": [],
    "top_accords": [],
    "accord_intensity": {},
    "community_longevity": null,
    "community_sillage": null,
    "community_projection": null,
    "compliment_score": null,
    "versatility_score": null,
    "office_safe_score": null,
    "price_tier": null,
    "retail_msrp_usd_cents": null,
    "prices": [],
    "image_url": "https://cdn.shopify.com/s/files/1/0722/1421/7014/files/8136219328822-e2ad9d4178a158f062838d04a03c8c46b1b62d72.jpg?v=1768397519",
    "source": "molinard",
    "source_url": "https://www.molinard.com/products/habanita-la-cologne",
    "sources": [
      "molinard"
    ]
  },
  {
    "brand": "Molinard",
    "name": "Parfum d'Ambiance 170",
    "release_year": null,
    "concentration": "parfum",
    "fragrance_family": null,
    "gender": "unisex",
    "top_notes": [],
    "heart_notes": [],
    "base_notes": [],
    "top_accords": [],
    "accord_intensity": {},
    "community_longevity": null,
    "community_sillage": null,
    "community_projection": null,
    "compliment_score": null,
    "versatility_score": null,
    "office_safe_score": null,
    "price_tier": null,
    "retail_msrp_usd_cents": null,
    "prices": [],
    "image_url": "https://cdn.shopify.com/s/files/1/0722/1421/7014/files/8190185636150-e6dd4e7f78609627d91d93258a760a6f9c478aed.jpg?v=1768397478",
    "source": "molinard",
    "source_url": "https://www.molinard.com/products/170-1",
    "sources": [
      "molinard"
    ]
  },
  {
    "brand": "Molinard",
    "name": "Parfum d'Ambiance Méditerranée",
    "release_year": null,
    "concentration": "parfum",
    "fragrance_family": null,
    "gender": "unisex",
    "top_notes": [],
    "heart_notes": [],
    "base_notes": [],
    "top_accords": [],
    "accord_intensity": {},
    "community_longevity": null,
    "community_sillage": null,
    "community_projection": null,
    "compliment_score": null,
    "versatility_score": null,
    "office_safe_score": null,
    "price_tier": null,
    "retail_msrp_usd_cents": null,
    "prices": [],
    "image_url": "https://cdn.shopify.com/s/files/1/0722/1421/7014/files/8190225056054-0f46712eab48ba60f102d5b0a5f818ff5dde3ede.jpg?v=1768397472",
    "source": "molinard",
    "source_url": "https://www.molinard.com/products/mediterrannee-2",
    "sources": [
      "molinard"
    ]
  },
  {
    "brand": "Molinard",
    "name": "Parfum d'Ambiance Osmanthus",
    "release_year": null,
    "concentration": "parfum",
    "fragrance_family": null,
    "gender": "unisex",
    "top_notes": [],
    "heart_notes": [],
    "base_notes": [],
    "top_accords": [],
    "accord_intensity": {},
    "community_longevity": null,
    "community_sillage": null,
    "community_projection": null,
    "compliment_score": null,
    "versatility_score": null,
    "office_safe_score": null,
    "price_tier": null,
    "retail_msrp_usd_cents": null,
    "prices": [],
    "image_url": "https://cdn.shopify.com/s/files/1/0722/1421/7014/files/8497931682127-f9bfd8371189e7dbd9e528b345007219ff571f72.jpg?v=1768397501",
    "source": "molinard",
    "source_url": "https://www.molinard.com/products/parfum-dambiance-osmanthus",
    "sources": [
      "molinard"
    ]
  },
  {
    "brand": "Molinard",
    "name": "Parfum d'Ambiance Thé Basilic",
    "release_year": null,
    "concentration": "parfum",
    "fragrance_family": null,
    "gender": "unisex",
    "top_notes": [],
    "heart_notes": [],
    "base_notes": [],
    "top_accords": [],
    "accord_intensity": {},
    "community_longevity": null,
    "community_sillage": null,
    "community_projection": null,
    "compliment_score": null,
    "versatility_score": null,
    "office_safe_score": null,
    "price_tier": null,
    "retail_msrp_usd_cents": null,
    "prices": [],
    "image_url": "https://cdn.shopify.com/s/files/1/0722/1421/7014/files/8190225645878-cf8e66b0793d8eff7e11b3074b84429a8ade274a.jpg?v=1768397461",
    "source": "molinard",
    "source_url": "https://www.molinard.com/products/the-basilic-2",
    "sources": [
      "molinard"
    ]
  },
  {
    "brand": "Molinard",
    "name": "Parfum d'Ambiance Tubéreuse",
    "release_year": null,
    "concentration": "parfum",
    "fragrance_family": null,
    "gender": "unisex",
    "top_notes": [],
    "heart_notes": [],
    "base_notes": [],
    "top_accords": [],
    "accord_intensity": {},
    "community_longevity": null,
    "community_sillage": null,
    "community_projection": null,
    "compliment_score": null,
    "versatility_score": null,
    "office_safe_score": null,
    "price_tier": null,
    "retail_msrp_usd_cents": null,
    "prices": [],
    "image_url": "https://cdn.shopify.com/s/files/1/0722/1421/7014/files/8190229152054-529bd8d0e37342d18c0f5d65b2abb68b8d4942ca.jpg?v=1768397490",
    "source": "molinard",
    "source_url": "https://www.molinard.com/products/tubereuse-1",
    "sources": [
      "molinard"
    ]
  },
  {
    "brand": "Molinard",
    "name": "Roll-on Bambou",
    "release_year": null,
    "concentration": "edp",
    "fragrance_family": null,
    "gender": "unisex",
    "top_notes": [],
    "heart_notes": [],
    "base_notes": [],
    "top_accords": [],
    "accord_intensity": {},
    "community_longevity": null,
    "community_sillage": null,
    "community_projection": null,
    "compliment_score": null,
    "versatility_score": null,
    "office_safe_score": null,
    "price_tier": null,
    "retail_msrp_usd_cents": null,
    "prices": [],
    "image_url": "https://cdn.shopify.com/s/files/1/0722/1421/7014/files/8516136403279-272aeb47e45a2147df2666a709c9f17a8e8a6cf0_980fd8f8-3079-4515-bdab-5a3c24bea7bc.jpg?v=1768220747",
    "source": "molinard",
    "source_url": "https://www.molinard.com/products/roll-on-bambou",
    "sources": [
      "molinard"
    ]
  },
  {
    "brand": "Molinard",
    "name": "Roll-on Bel Air",
    "release_year": null,
    "concentration": "edp",
    "fragrance_family": null,
    "gender": "unisex",
    "top_notes": [],
    "heart_notes": [],
    "base_notes": [],
    "top_accords": [],
    "accord_intensity": {},
    "community_longevity": null,
    "community_sillage": null,
    "community_projection": null,
    "compliment_score": null,
    "versatility_score": null,
    "office_safe_score": null,
    "price_tier": null,
    "retail_msrp_usd_cents": null,
    "prices": [],
    "image_url": "https://cdn.shopify.com/s/files/1/0722/1421/7014/files/8195352953142-1a7d041478e2459632a6a565df8310ffed8f5f1f_17f021a0-4245-4e0d-a88e-1da9add9c1aa.jpg?v=1768220300",
    "source": "molinard",
    "source_url": "https://www.molinard.com/products/roll-on-bel-air",
    "sources": [
      "molinard"
    ]
  },
  {
    "brand": "Molinard",
    "name": "Roll-on Campus",
    "release_year": null,
    "concentration": "edp",
    "fragrance_family": null,
    "gender": "unisex",
    "top_notes": [],
    "heart_notes": [],
    "base_notes": [],
    "top_accords": [],
    "accord_intensity": {},
    "community_longevity": null,
    "community_sillage": null,
    "community_projection": null,
    "compliment_score": null,
    "versatility_score": null,
    "office_safe_score": null,
    "price_tier": null,
    "retail_msrp_usd_cents": null,
    "prices": [],
    "image_url": "https://cdn.shopify.com/s/files/1/0722/1421/7014/files/8195379200310-3c6c65388f5c9b413995a6e75691443d833349e3_30910d64-414c-4764-8cbc-12c39cea3048.jpg?v=1768220758",
    "source": "molinard",
    "source_url": "https://www.molinard.com/products/roll-on-campus",
    "sources": [
      "molinard"
    ]
  },
  {
    "brand": "Molinard",
    "name": "Roll-on Chypre Charnel",
    "release_year": null,
    "concentration": "edp",
    "fragrance_family": null,
    "gender": "unisex",
    "top_notes": [],
    "heart_notes": [],
    "base_notes": [],
    "top_accords": [],
    "accord_intensity": {},
    "community_longevity": null,
    "community_sillage": null,
    "community_projection": null,
    "compliment_score": null,
    "versatility_score": null,
    "office_safe_score": null,
    "price_tier": null,
    "retail_msrp_usd_cents": null,
    "prices": [],
    "image_url": "https://cdn.shopify.com/s/files/1/0722/1421/7014/files/8480522273103-0b3b65ff93d4029043e191ff928a5d4ead3c690c_442bd04e-c6e4-4a92-9447-f1149bf69917.jpg?v=1768220765",
    "source": "molinard",
    "source_url": "https://www.molinard.com/products/roll-on-chypre-charnel",
    "sources": [
      "molinard"
    ]
  },
  {
    "brand": "Molinard",
    "name": "Roll-on Citrus Noir",
    "release_year": null,
    "concentration": "edp",
    "fragrance_family": null,
    "gender": "unisex",
    "top_notes": [],
    "heart_notes": [],
    "base_notes": [],
    "top_accords": [],
    "accord_intensity": {},
    "community_longevity": null,
    "community_sillage": null,
    "community_projection": null,
    "compliment_score": null,
    "versatility_score": null,
    "office_safe_score": null,
    "price_tier": null,
    "retail_msrp_usd_cents": null,
    "prices": [],
    "image_url": "https://cdn.shopify.com/s/files/1/0722/1421/7014/files/8194525856054-55ca5b001d9fdc6fbb9abe5997c408d98ce34404_72e13f65-1fc2-4e68-a4c5-68798cc7dd2e.jpg?v=1768220770",
    "source": "molinard",
    "source_url": "https://www.molinard.com/products/roll-on-citrus-noir",
    "sources": [
      "molinard"
    ]
  },
  {
    "brand": "Molinard",
    "name": "Roll-on Cuir",
    "release_year": null,
    "concentration": "edp",
    "fragrance_family": null,
    "gender": "unisex",
    "top_notes": [],
    "heart_notes": [],
    "base_notes": [],
    "top_accords": [],
    "accord_intensity": {},
    "community_longevity": null,
    "community_sillage": null,
    "community_projection": null,
    "compliment_score": null,
    "versatility_score": null,
    "office_safe_score": null,
    "price_tier": null,
    "retail_msrp_usd_cents": null,
    "prices": [],
    "image_url": "https://cdn.shopify.com/s/files/1/0722/1421/7014/files/8194895249718-723d4b83bb9acb5a533ac1dea3179c3d61b0736b_741cf227-b6d1-47dc-a7c1-c1c1a3f6d98a.jpg?v=1768220776",
    "source": "molinard",
    "source_url": "https://www.molinard.com/products/roll-on-cuir",
    "sources": [
      "molinard"
    ]
  },
  {
    "brand": "Molinard",
    "name": "Roll-on Figue",
    "release_year": null,
    "concentration": "edp",
    "fragrance_family": null,
    "gender": "unisex",
    "top_notes": [],
    "heart_notes": [],
    "base_notes": [],
    "top_accords": [],
    "accord_intensity": {},
    "community_longevity": null,
    "community_sillage": null,
    "community_projection": null,
    "compliment_score": null,
    "versatility_score": null,
    "office_safe_score": null,
    "price_tier": null,
    "retail_msrp_usd_cents": null,
    "prices": [],
    "image_url": "https://cdn.shopify.com/s/files/1/0722/1421/7014/files/8194906489142-372eafe31c5069d10db399d27b4b6126ac26abce_fb1d8653-c724-4bfd-84ce-29d942c774a0.jpg?v=1768220782",
    "source": "molinard",
    "source_url": "https://www.molinard.com/products/roll-on-figue",
    "sources": [
      "molinard"
    ]
  },
  {
    "brand": "Molinard",
    "name": "Roll-on Fleur d'Oranger",
    "release_year": null,
    "concentration": "edp",
    "fragrance_family": null,
    "gender": "unisex",
    "top_notes": [],
    "heart_notes": [],
    "base_notes": [],
    "top_accords": [],
    "accord_intensity": {},
    "community_longevity": null,
    "community_sillage": null,
    "community_projection": null,
    "compliment_score": null,
    "versatility_score": null,
    "office_safe_score": null,
    "price_tier": null,
    "retail_msrp_usd_cents": null,
    "prices": [],
    "image_url": "https://cdn.shopify.com/s/files/1/0722/1421/7014/files/8194912485686-a5e99d8d74a4513d5c833c609f6692139f88cea6_b10bbd82-2e04-48ca-9ae6-3f52334f91d8.jpg?v=1768220787",
    "source": "molinard",
    "source_url": "https://www.molinard.com/products/roll-on-fleur-doranger",
    "sources": [
      "molinard"
    ]
  },
  {
    "brand": "Molinard",
    "name": "Roll-on Gingembre",
    "release_year": null,
    "concentration": "edp",
    "fragrance_family": null,
    "gender": "unisex",
    "top_notes": [],
    "heart_notes": [],
    "base_notes": [],
    "top_accords": [],
    "accord_intensity": {},
    "community_longevity": null,
    "community_sillage": null,
    "community_projection": null,
    "compliment_score": null,
    "versatility_score": null,
    "office_safe_score": null,
    "price_tier": null,
    "retail_msrp_usd_cents": null,
    "prices": [],
    "image_url": "https://cdn.shopify.com/s/files/1/0722/1421/7014/files/8194876834102-e7f9948750de6571ba790b97cf94238c0873ed82_e5f723cd-26db-49b1-854a-e79616ae837b.jpg?v=1768220793",
    "source": "molinard",
    "source_url": "https://www.molinard.com/products/roll-on-gingembre",
    "sources": [
      "molinard"
    ]
  },
  {
    "brand": "Molinard",
    "name": "Roll-On Habanita",
    "release_year": null,
    "concentration": "edp",
    "fragrance_family": null,
    "gender": "unisex",
    "top_notes": [],
    "heart_notes": [],
    "base_notes": [],
    "top_accords": [],
    "accord_intensity": {},
    "community_longevity": null,
    "community_sillage": null,
    "community_projection": null,
    "compliment_score": null,
    "versatility_score": null,
    "office_safe_score": null,
    "price_tier": null,
    "retail_msrp_usd_cents": null,
    "prices": [],
    "image_url": "https://cdn.shopify.com/s/files/1/0722/1421/7014/files/8136249475382-a87c82e7eac3cd2f5b9e48d59f97c8a02d33885a_49fd4846-89a5-4e64-a4eb-b8f9dc53336b.jpg?v=1768220798",
    "source": "molinard",
    "source_url": "https://www.molinard.com/products/habanita-roll-on",
    "sources": [
      "molinard"
    ]
  },
  {
    "brand": "Molinard",
    "name": "Roll-on Habanita L'Esprit",
    "release_year": null,
    "concentration": "edp",
    "fragrance_family": null,
    "gender": "unisex",
    "top_notes": [],
    "heart_notes": [],
    "base_notes": [],
    "top_accords": [],
    "accord_intensity": {},
    "community_longevity": null,
    "community_sillage": null,
    "community_projection": null,
    "compliment_score": null,
    "versatility_score": null,
    "office_safe_score": null,
    "price_tier": null,
    "retail_msrp_usd_cents": null,
    "prices": [],
    "image_url": "https://cdn.shopify.com/s/files/1/0722/1421/7014/files/8480544325967-78f3b0791f8532c6b0ac4e60d8ab52d299d49261_712ea9b2-0815-432f-acdd-a12a0bb18a93.jpg?v=1768220965",
    "source": "molinard",
    "source_url": "https://www.molinard.com/products/roll-on-habanita-lesprit",
    "sources": [
      "molinard"
    ]
  },
  {
    "brand": "Molinard",
    "name": "Roll-on Îles d'Or",
    "release_year": null,
    "concentration": "edp",
    "fragrance_family": null,
    "gender": "unisex",
    "top_notes": [],
    "heart_notes": [],
    "base_notes": [],
    "top_accords": [],
    "accord_intensity": {},
    "community_longevity": null,
    "community_sillage": null,
    "community_projection": null,
    "compliment_score": null,
    "versatility_score": null,
    "office_safe_score": null,
    "price_tier": null,
    "retail_msrp_usd_cents": null,
    "prices": [],
    "image_url": "https://cdn.shopify.com/s/files/1/0722/1421/7014/files/8197309825334-42dbd9b28c4d51e531864e9d98318ff0267e5b61_aaec8996-1672-4937-8e23-ffd8333b82f5.jpg?v=1768220804",
    "source": "molinard",
    "source_url": "https://www.molinard.com/products/roll-on-iles-dor",
    "sources": [
      "molinard"
    ]
  },
  {
    "brand": "Molinard",
    "name": "Roll-on Iris",
    "release_year": null,
    "concentration": "edp",
    "fragrance_family": null,
    "gender": "unisex",
    "top_notes": [],
    "heart_notes": [],
    "base_notes": [],
    "top_accords": [],
    "accord_intensity": {},
    "community_longevity": null,
    "community_sillage": null,
    "community_projection": null,
    "compliment_score": null,
    "versatility_score": null,
    "office_safe_score": null,
    "price_tier": null,
    "retail_msrp_usd_cents": null,
    "prices": [],
    "image_url": "https://cdn.shopify.com/s/files/1/0722/1421/7014/files/8820314898767-3474e7d2f0f6b6aae7662e2cfe97efb722f067c6.jpg?v=1768469499",
    "source": "molinard",
    "source_url": "https://www.molinard.com/products/roll-on-iris",
    "sources": [
      "molinard"
    ]
  },
  {
    "brand": "Molinard",
    "name": "Roll-on Iris Ardent",
    "release_year": null,
    "concentration": "edp",
    "fragrance_family": null,
    "gender": "unisex",
    "top_notes": [],
    "heart_notes": [],
    "base_notes": [],
    "top_accords": [],
    "accord_intensity": {},
    "community_longevity": null,
    "community_sillage": null,
    "community_projection": null,
    "compliment_score": null,
    "versatility_score": null,
    "office_safe_score": null,
    "price_tier": null,
    "retail_msrp_usd_cents": null,
    "prices": [],
    "image_url": "https://cdn.shopify.com/s/files/1/0722/1421/7014/files/9421097795919-b2bb301bca6198c54912bf1e017a7223d9f24803_28c3425a-fe9d-4bec-9cea-40d08905bb50.jpg?v=1768220809",
    "source": "molinard",
    "source_url": "https://www.molinard.com/products/roll-on-iris-ardent",
    "sources": [
      "molinard"
    ]
  },
  {
    "brand": "Molinard",
    "name": "Roll-on Jasmin",
    "release_year": null,
    "concentration": "edp",
    "fragrance_family": null,
    "gender": "unisex",
    "top_notes": [],
    "heart_notes": [],
    "base_notes": [],
    "top_accords": [],
    "accord_intensity": {},
    "community_longevity": null,
    "community_sillage": null,
    "community_projection": null,
    "compliment_score": null,
    "versatility_score": null,
    "office_safe_score": null,
    "price_tier": null,
    "retail_msrp_usd_cents": null,
    "prices": [],
    "image_url": "https://cdn.shopify.com/s/files/1/0722/1421/7014/files/8194919956790-d0753ade087744ef55538b711103593cea4dcf8f_e8bed90e-8db5-4e29-9344-57f08d1e7aca.jpg?v=1768220820",
    "source": "molinard",
    "source_url": "https://www.molinard.com/products/roll-on-jasmin",
    "sources": [
      "molinard"
    ]
  },
  {
    "brand": "Molinard",
    "name": "Roll-on Lavande",
    "release_year": null,
    "concentration": "edp",
    "fragrance_family": null,
    "gender": "unisex",
    "top_notes": [],
    "heart_notes": [],
    "base_notes": [],
    "top_accords": [],
    "accord_intensity": {},
    "community_longevity": null,
    "community_sillage": null,
    "community_projection": null,
    "compliment_score": null,
    "versatility_score": null,
    "office_safe_score": null,
    "price_tier": null,
    "retail_msrp_usd_cents": null,
    "prices": [],
    "image_url": "https://cdn.shopify.com/s/files/1/0722/1421/7014/files/8195000205622-e198877987868c5da04127659b1ea1ef6b98c601_0cefbdcf-cefb-4871-82e2-1c40bbe411e8.jpg?v=1768220825",
    "source": "molinard",
    "source_url": "https://www.molinard.com/products/roll-on-lavande",
    "sources": [
      "molinard"
    ]
  },
  {
    "brand": "Molinard",
    "name": "Roll-on Le Rêve Nirmala",
    "release_year": null,
    "concentration": "edp",
    "fragrance_family": null,
    "gender": "unisex",
    "top_notes": [],
    "heart_notes": [],
    "base_notes": [],
    "top_accords": [],
    "accord_intensity": {},
    "community_longevity": null,
    "community_sillage": null,
    "community_projection": null,
    "compliment_score": null,
    "versatility_score": null,
    "office_safe_score": null,
    "price_tier": null,
    "retail_msrp_usd_cents": null,
    "prices": [],
    "image_url": "https://cdn.shopify.com/s/files/1/0722/1421/7014/files/8197317001526-2a0ad1fa6f3ca776d109318d0da054f1c274753a_ea8f4241-7012-4095-9883-97d73c47878c.jpg?v=1768220960",
    "source": "molinard",
    "source_url": "https://www.molinard.com/products/roll-on-le-reve-nirmala",
    "sources": [
      "molinard"
    ]
  },
  {
    "brand": "Molinard",
    "name": "Roll-on Madrigal",
    "release_year": null,
    "concentration": "edp",
    "fragrance_family": null,
    "gender": "unisex",
    "top_notes": [],
    "heart_notes": [],
    "base_notes": [],
    "top_accords": [],
    "accord_intensity": {},
    "community_longevity": null,
    "community_sillage": null,
    "community_projection": null,
    "compliment_score": null,
    "versatility_score": null,
    "office_safe_score": null,
    "price_tier": null,
    "retail_msrp_usd_cents": null,
    "prices": [],
    "image_url": "https://cdn.shopify.com/s/files/1/0722/1421/7014/files/8197324407094-9d53ac647d2dcf30254d4f56c2f2a565fe5044a2_2bf278d7-4ec2-4b3d-b0c4-77bacca6dac0.jpg?v=1768220837",
    "source": "molinard",
    "source_url": "https://www.molinard.com/products/roll-on-madrigal",
    "sources": [
      "molinard"
    ]
  },
  {
    "brand": "Molinard",
    "name": "Roll-on Méditérranée",
    "release_year": null,
    "concentration": "edp",
    "fragrance_family": null,
    "gender": "unisex",
    "top_notes": [],
    "heart_notes": [],
    "base_notes": [],
    "top_accords": [],
    "accord_intensity": {},
    "community_longevity": null,
    "community_sillage": null,
    "community_projection": null,
    "compliment_score": null,
    "versatility_score": null,
    "office_safe_score": null,
    "price_tier": null,
    "retail_msrp_usd_cents": null,
    "prices": [],
    "image_url": "https://cdn.shopify.com/s/files/1/0722/1421/7014/files/8194885681462-0aa4848affff87facd5eef54e8a12e1c19ee450b_72a300d8-e03b-4315-aa3f-596c376bbed6.jpg?v=1768220842",
    "source": "molinard",
    "source_url": "https://www.molinard.com/products/roll-on-mediterrannee",
    "sources": [
      "molinard"
    ]
  },
  {
    "brand": "Molinard",
    "name": "Roll-on Miréa",
    "release_year": null,
    "concentration": "edp",
    "fragrance_family": null,
    "gender": "unisex",
    "top_notes": [],
    "heart_notes": [],
    "base_notes": [],
    "top_accords": [],
    "accord_intensity": {},
    "community_longevity": null,
    "community_sillage": null,
    "community_projection": null,
    "compliment_score": null,
    "versatility_score": null,
    "office_safe_score": null,
    "price_tier": null,
    "retail_msrp_usd_cents": null,
    "prices": [],
    "image_url": "https://cdn.shopify.com/s/files/1/0722/1421/7014/files/8197327159606-7db1802b6b00f8a12ef8ee2c9eb8ae5be1eaa31a_cd5befb9-0352-4f29-8116-eee0daa666bb.jpg?v=1768220848",
    "source": "molinard",
    "source_url": "https://www.molinard.com/products/roll-on-mirea",
    "sources": [
      "molinard"
    ]
  },
  {
    "brand": "Molinard",
    "name": "Roll-on MM",
    "release_year": null,
    "concentration": "edp",
    "fragrance_family": null,
    "gender": "unisex",
    "top_notes": [],
    "heart_notes": [],
    "base_notes": [],
    "top_accords": [],
    "accord_intensity": {},
    "community_longevity": null,
    "community_sillage": null,
    "community_projection": null,
    "compliment_score": null,
    "versatility_score": null,
    "office_safe_score": null,
    "price_tier": null,
    "retail_msrp_usd_cents": null,
    "prices": [],
    "image_url": "https://cdn.shopify.com/s/files/1/0722/1421/7014/files/8197329813814-aa7f3fb461b0d6193298705f71141489cc87fa81_b455b8c4-89b5-4322-8019-d0ce08ab2180.jpg?v=1768220854",
    "source": "molinard",
    "source_url": "https://www.molinard.com/products/roll-on-mm",
    "sources": [
      "molinard"
    ]
  },
  {
    "brand": "Molinard",
    "name": "Roll-on Muguet",
    "release_year": null,
    "concentration": "edp",
    "fragrance_family": null,
    "gender": "unisex",
    "top_notes": [],
    "heart_notes": [],
    "base_notes": [],
    "top_accords": [],
    "accord_intensity": {},
    "community_longevity": null,
    "community_sillage": null,
    "community_projection": null,
    "compliment_score": null,
    "versatility_score": null,
    "office_safe_score": null,
    "price_tier": null,
    "retail_msrp_usd_cents": null,
    "prices": [],
    "image_url": "https://cdn.shopify.com/s/files/1/0722/1421/7014/files/8195190784310-aa771f22a6db9adbbb6022a22359d05f5119bf9d_4e61ff98-417e-4199-bbe4-2589bb895051.jpg?v=1768220859",
    "source": "molinard",
    "source_url": "https://www.molinard.com/products/roll-on-muguet",
    "sources": [
      "molinard"
    ]
  },
  {
    "brand": "Molinard",
    "name": "Roll-on Nirmala",
    "release_year": null,
    "concentration": "edp",
    "fragrance_family": null,
    "gender": "unisex",
    "top_notes": [],
    "heart_notes": [],
    "base_notes": [],
    "top_accords": [],
    "accord_intensity": {},
    "community_longevity": null,
    "community_sillage": null,
    "community_projection": null,
    "compliment_score": null,
    "versatility_score": null,
    "office_safe_score": null,
    "price_tier": null,
    "retail_msrp_usd_cents": null,
    "prices": [],
    "image_url": "https://cdn.shopify.com/s/files/1/0722/1421/7014/files/8197336891702-71716bd54a759d56ac7e53a4a9e6c9286865db17_ecc2b617-3186-4f00-b963-eb6a7700ba39.jpg?v=1768220971",
    "source": "molinard",
    "source_url": "https://www.molinard.com/products/roll-on-nirmala",
    "sources": [
      "molinard"
    ]
  },
  {
    "brand": "Molinard",
    "name": "Roll-on Osmanthus",
    "release_year": null,
    "concentration": "edp",
    "fragrance_family": null,
    "gender": "unisex",
    "top_notes": [],
    "heart_notes": [],
    "base_notes": [],
    "top_accords": [],
    "accord_intensity": {},
    "community_longevity": null,
    "community_sillage": null,
    "community_projection": null,
    "compliment_score": null,
    "versatility_score": null,
    "office_safe_score": null,
    "price_tier": null,
    "retail_msrp_usd_cents": null,
    "prices": [],
    "image_url": "https://cdn.shopify.com/s/files/1/0722/1421/7014/files/8195193078070-763d016a4bd0269686b6bcdbd3f8cf2cd6218c76_350abf04-0e89-4265-8a53-443028792a16.jpg?v=1768220871",
    "source": "molinard",
    "source_url": "https://www.molinard.com/products/roll-on-osmanthus",
    "sources": [
      "molinard"
    ]
  },
  {
    "brand": "Molinard",
    "name": "Roll-on Oud Magnétique",
    "release_year": null,
    "concentration": "edp",
    "fragrance_family": null,
    "gender": "unisex",
    "top_notes": [],
    "heart_notes": [],
    "base_notes": [],
    "top_accords": [],
    "accord_intensity": {},
    "community_longevity": null,
    "community_sillage": null,
    "community_projection": null,
    "compliment_score": null,
    "versatility_score": null,
    "office_safe_score": null,
    "price_tier": null,
    "retail_msrp_usd_cents": null,
    "prices": [],
    "image_url": "https://cdn.shopify.com/s/files/1/0722/1421/7014/files/8480530596175-c85b567f8471153105d0585fb1329423ccc6af63_176eefb2-f7e6-4b4c-bfb8-4b66def63dff.jpg?v=1768220877",
    "source": "molinard",
    "source_url": "https://www.molinard.com/products/roll-on-oud-magnetique",
    "sources": [
      "molinard"
    ]
  },
  {
    "brand": "Molinard",
    "name": "Roll-on Patchouli",
    "release_year": null,
    "concentration": "edp",
    "fragrance_family": null,
    "gender": "unisex",
    "top_notes": [],
    "heart_notes": [],
    "base_notes": [],
    "top_accords": [],
    "accord_intensity": {},
    "community_longevity": null,
    "community_sillage": null,
    "community_projection": null,
    "compliment_score": null,
    "versatility_score": null,
    "office_safe_score": null,
    "price_tier": null,
    "retail_msrp_usd_cents": null,
    "prices": [],
    "image_url": "https://cdn.shopify.com/s/files/1/0722/1421/7014/files/8195197862198-f0576e547a40200900969a9e5e7c62d4064c14e8_fa1cb140-ec08-4f1c-8348-e82fadf0baa3.jpg?v=1768220882",
    "source": "molinard",
    "source_url": "https://www.molinard.com/products/roll-on-patchouli",
    "sources": [
      "molinard"
    ]
  },
  {
    "brand": "Molinard",
    "name": "Roll-on Patchouli Intense",
    "release_year": null,
    "concentration": "edp",
    "fragrance_family": null,
    "gender": "unisex",
    "top_notes": [],
    "heart_notes": [],
    "base_notes": [],
    "top_accords": [],
    "accord_intensity": {},
    "community_longevity": null,
    "community_sillage": null,
    "community_projection": null,
    "compliment_score": null,
    "versatility_score": null,
    "office_safe_score": null,
    "price_tier": null,
    "retail_msrp_usd_cents": null,
    "prices": [],
    "image_url": "https://cdn.shopify.com/s/files/1/0722/1421/7014/files/8480532201807-b993fbe3dd3f4c0338f9096807db39d04bf62bff_7c24baba-5a95-48df-8321-6615e380913b.jpg?v=1768220888",
    "source": "molinard",
    "source_url": "https://www.molinard.com/products/roll-on-patchouli-intense",
    "sources": [
      "molinard"
    ]
  },
  {
    "brand": "Molinard",
    "name": "Roll-on Rose",
    "release_year": null,
    "concentration": "edp",
    "fragrance_family": null,
    "gender": "unisex",
    "top_notes": [],
    "heart_notes": [],
    "base_notes": [],
    "top_accords": [],
    "accord_intensity": {},
    "community_longevity": null,
    "community_sillage": null,
    "community_projection": null,
    "compliment_score": null,
    "versatility_score": null,
    "office_safe_score": null,
    "price_tier": null,
    "retail_msrp_usd_cents": null,
    "prices": [],
    "image_url": "https://cdn.shopify.com/s/files/1/0722/1421/7014/files/8195203170614-c6657c4c2253581ddbde9ba9a162d40bb424107e_d3c125a5-68fb-45c8-8c38-e9a5e3166eb4.jpg?v=1768220894",
    "source": "molinard",
    "source_url": "https://www.molinard.com/products/roll-on-rose",
    "sources": [
      "molinard"
    ]
  },
  {
    "brand": "Molinard",
    "name": "Roll-on Santal Insolent",
    "release_year": null,
    "concentration": "edp",
    "fragrance_family": null,
    "gender": "unisex",
    "top_notes": [],
    "heart_notes": [],
    "base_notes": [],
    "top_accords": [],
    "accord_intensity": {},
    "community_longevity": null,
    "community_sillage": null,
    "community_projection": null,
    "compliment_score": null,
    "versatility_score": null,
    "office_safe_score": null,
    "price_tier": null,
    "retail_msrp_usd_cents": null,
    "prices": [],
    "image_url": "https://cdn.shopify.com/s/files/1/0722/1421/7014/files/8480537411919-e6838fb330894020bace90edf459b0adf472fe4b_bf4f292e-3ae5-493e-990d-d451a62b7614.jpg?v=1768220909",
    "source": "molinard",
    "source_url": "https://www.molinard.com/products/roll-on-santal-insolent",
    "sources": [
      "molinard"
    ]
  },
  {
    "brand": "Molinard",
    "name": "Roll-on Thé Basilic",
    "release_year": null,
    "concentration": "edp",
    "fragrance_family": null,
    "gender": "unisex",
    "top_notes": [],
    "heart_notes": [],
    "base_notes": [],
    "top_accords": [],
    "accord_intensity": {},
    "community_longevity": null,
    "community_sillage": null,
    "community_projection": null,
    "compliment_score": null,
    "versatility_score": null,
    "office_safe_score": null,
    "price_tier": null,
    "retail_msrp_usd_cents": null,
    "prices": [],
    "image_url": "https://cdn.shopify.com/s/files/1/0722/1421/7014/files/8194536669494-a5f5660a9c21c0c3b4c27acc1ee7f79b58a36256_4ed8b733-b7b8-4dd3-a9b5-9026f0b64845.jpg?v=1768220915",
    "source": "molinard",
    "source_url": "https://www.molinard.com/products/roll-on-the-basilic",
    "sources": [
      "molinard"
    ]
  },
  {
    "brand": "Molinard",
    "name": "Roll-on Tubéreuse Vertigineuse",
    "release_year": null,
    "concentration": "edp",
    "fragrance_family": null,
    "gender": "unisex",
    "top_notes": [],
    "heart_notes": [],
    "base_notes": [],
    "top_accords": [],
    "accord_intensity": {},
    "community_longevity": null,
    "community_sillage": null,
    "community_projection": null,
    "compliment_score": null,
    "versatility_score": null,
    "office_safe_score": null,
    "price_tier": null,
    "retail_msrp_usd_cents": null,
    "prices": [],
    "image_url": "https://cdn.shopify.com/s/files/1/0722/1421/7014/files/8480539476303-603a501d2e24ead35b173d4857a2cd76b7d9d95d_cb95c862-f03f-4aaa-abf3-1e022ebf09cb.jpg?v=1768220921",
    "source": "molinard",
    "source_url": "https://www.molinard.com/products/roll-on-tubereuse-vertigineuse",
    "sources": [
      "molinard"
    ]
  },
  {
    "brand": "Molinard",
    "name": "Roll-on Vanille",
    "release_year": null,
    "concentration": "edp",
    "fragrance_family": null,
    "gender": "unisex",
    "top_notes": [],
    "heart_notes": [],
    "base_notes": [],
    "top_accords": [],
    "accord_intensity": {},
    "community_longevity": null,
    "community_sillage": null,
    "community_projection": null,
    "compliment_score": null,
    "versatility_score": null,
    "office_safe_score": null,
    "price_tier": null,
    "retail_msrp_usd_cents": null,
    "prices": [],
    "image_url": "https://cdn.shopify.com/s/files/1/0722/1421/7014/files/8195268772150-6e37ab02acdeb06492f16a4de9fae7c791478cb4_8aabb6b2-ab2d-42ac-a560-0f301befe40d.jpg?v=1768220926",
    "source": "molinard",
    "source_url": "https://www.molinard.com/products/roll-on-vanille",
    "sources": [
      "molinard"
    ]
  },
  {
    "brand": "Molinard",
    "name": "Roll-on Vents et Marées",
    "release_year": null,
    "concentration": "edp",
    "fragrance_family": null,
    "gender": "unisex",
    "top_notes": [],
    "heart_notes": [],
    "base_notes": [],
    "top_accords": [],
    "accord_intensity": {},
    "community_longevity": null,
    "community_sillage": null,
    "community_projection": null,
    "compliment_score": null,
    "versatility_score": null,
    "office_safe_score": null,
    "price_tier": null,
    "retail_msrp_usd_cents": null,
    "prices": [],
    "image_url": "https://cdn.shopify.com/s/files/1/0722/1421/7014/files/8197339873590-80d6792f2de4e02e80505904dd53e7fcee8c39ec_dca82ca9-97dc-4deb-880f-2379078e793c.jpg?v=1768220943",
    "source": "molinard",
    "source_url": "https://www.molinard.com/products/roll-on-vents-marees",
    "sources": [
      "molinard"
    ]
  },
  {
    "brand": "Molinard",
    "name": "Roll-on Vétiver",
    "release_year": null,
    "concentration": "edp",
    "fragrance_family": null,
    "gender": "unisex",
    "top_notes": [],
    "heart_notes": [],
    "base_notes": [],
    "top_accords": [],
    "accord_intensity": {},
    "community_longevity": null,
    "community_sillage": null,
    "community_projection": null,
    "compliment_score": null,
    "versatility_score": null,
    "office_safe_score": null,
    "price_tier": null,
    "retail_msrp_usd_cents": null,
    "prices": [],
    "image_url": "https://cdn.shopify.com/s/files/1/0722/1421/7014/files/8195274146102-1c859aac0858e3bf425404a16b502dc1150c6046_4b102a89-8f58-416b-acfc-9c42cf293ee3.jpg?v=1768220949",
    "source": "molinard",
    "source_url": "https://www.molinard.com/products/roll-on-vetiver",
    "sources": [
      "molinard"
    ]
  },
  {
    "brand": "Molinard",
    "name": "Roll-on Violette",
    "release_year": null,
    "concentration": "edp",
    "fragrance_family": null,
    "gender": "unisex",
    "top_notes": [],
    "heart_notes": [],
    "base_notes": [],
    "top_accords": [],
    "accord_intensity": {},
    "community_longevity": null,
    "community_sillage": null,
    "community_projection": null,
    "compliment_score": null,
    "versatility_score": null,
    "office_safe_score": null,
    "price_tier": null,
    "retail_msrp_usd_cents": null,
    "prices": [],
    "image_url": "https://cdn.shopify.com/s/files/1/0722/1421/7014/files/8195284468022-a11f01f531385af43eaded57090d3f186bbee9d8_2de44785-79a8-4a3f-be25-1d7f278bab34.jpg?v=1768220954",
    "source": "molinard",
    "source_url": "https://www.molinard.com/products/roll-on-violette",
    "sources": [
      "molinard"
    ]
  }
]